{
  "OLS-3": {
    "oos_r2_pct": 0.142637,
    "hl_sharpe": 0.6113,
    "hl_sharpe_gross": 0.888611,
    "hl_mean_turnover_one_way": 1.558465,
    "hl_engine_tc_bps": 10.0,
    "hl_returns_are_net_of_tc": true
  },
  "ENet+H": {
    "oos_r2_pct": 0.053534,
    "hl_sharpe": 0.185841,
    "hl_sharpe_gross": 0.427466,
    "hl_mean_turnover_one_way": 1.561169,
    "hl_engine_tc_bps": 10.0,
    "hl_returns_are_net_of_tc": true
  },
  "PCR": {
    "oos_r2_pct": 0.097813,
    "hl_sharpe": 0.227094,
    "hl_sharpe_gross": 0.549132,
    "hl_mean_turnover_one_way": 1.547756,
    "hl_engine_tc_bps": 10.0,
    "hl_returns_are_net_of_tc": true
  },
  "PLS": {
    "oos_r2_pct": 0.159694,
    "hl_sharpe": 0.006495,
    "hl_sharpe_gross": 0.319687,
    "hl_mean_turnover_one_way": 1.550682,
    "hl_engine_tc_bps": 10.0,
    "hl_returns_are_net_of_tc": true
  },
  "GLM+H": {
    "oos_r2_pct": 0.110831,
    "hl_sharpe": 0.432783,
    "hl_sharpe_gross": 0.744791,
    "hl_mean_turnover_one_way": 1.549132,
    "hl_engine_tc_bps": 10.0,
    "hl_returns_are_net_of_tc": true
  },
  "GBRT+H": {
    "oos_r2_pct": 0.184532,
    "hl_sharpe": 0.473049,
    "hl_sharpe_gross": 0.754012,
    "hl_mean_turnover_one_way": 1.571875,
    "hl_engine_tc_bps": 10.0,
    "hl_returns_are_net_of_tc": true
  },
  "NN1": {
    "oos_r2_pct": 0.176222,
    "hl_sharpe": 1.106079,
    "hl_sharpe_gross": 1.38413,
    "hl_mean_turnover_one_way": 1.562011,
    "hl_engine_tc_bps": 10.0,
    "hl_returns_are_net_of_tc": true
  },
  "NN2": {
    "oos_r2_pct": 0.151508,
    "hl_sharpe": 1.449081,
    "hl_sharpe_gross": 1.723068,
    "hl_mean_turnover_one_way": 1.544659,
    "hl_engine_tc_bps": 10.0,
    "hl_returns_are_net_of_tc": true
  },
  "NN3": {
    "oos_r2_pct": 0.277132,
    "hl_sharpe": 0.669936,
    "hl_sharpe_gross": 0.970783,
    "hl_mean_turnover_one_way": 1.556008,
    "hl_engine_tc_bps": 10.0,
    "hl_returns_are_net_of_tc": true
  },
  "NN4": {
    "oos_r2_pct": 0.217499,
    "hl_sharpe": 1.17605,
    "hl_sharpe_gross": 1.427098,
    "hl_mean_turnover_one_way": 1.543879,
    "hl_engine_tc_bps": 10.0,
    "hl_returns_are_net_of_tc": true
  },
  "ENS-AVG": {
    "oos_r2_pct": 0.329787,
    "hl_sharpe": 1.636474,
    "hl_sharpe_gross": 1.89388,
    "hl_mean_turnover_one_way": 1.553612,
    "hl_engine_tc_bps": 10.0,
    "hl_returns_are_net_of_tc": true
  },
  "ENS-MSE": {
    "oos_r2_pct": 0.293002,
    "hl_sharpe": 1.323635,
    "hl_sharpe_gross": 1.582077,
    "hl_mean_turnover_one_way": 1.561504,
    "hl_engine_tc_bps": 10.0,
    "hl_returns_are_net_of_tc": true
  },
  "_reporting": {
    "variant": "future2026_mean_reversion",
    "scenario": "mean_reversion",
    "data_start": "2026-04-30",
    "data_end": "2036-03-31",
    "test_start": "2026-04-30",
    "test_end": "2036-03-31",
    "synthetic": true,
    "n_months": 120,
    "engine_tc_bps": 10.0,
    "panel_source": "synthetic_stock_level",
    "panel_path": "data/cache/synthetic_panels/future2026_mean_reversion.parquet",
    "n_stocks": 800,
    "n_rows": 96000,
    "panel_start": "2026-04-30",
    "panel_end": "2036-03-31"
  },
  "_ensembles": {
    "ENS-AVG": {
      "constituents": [
        "OLS-3",
        "ENet+H",
        "PCR",
        "PLS",
        "GLM+H",
        "GBRT+H",
        "NN1",
        "NN2",
        "NN3",
        "NN4"
      ],
      "_method": "assumed_uniform_average_over_constituents"
    },
    "ENS-MSE": {
      "constituents": [
        "OLS-3",
        "ENet+H",
        "PCR",
        "PLS",
        "GLM+H",
        "GBRT+H",
        "NN1",
        "NN2",
        "NN3",
        "NN4"
      ],
      "weights": {
        "OLS-3": 0.10003009677657344,
        "ENet+H": 0.09794836179883061,
        "PCR": 0.09873625194659588,
        "PLS": 0.09928209143232972,
        "GLM+H": 0.09713567504454315,
        "GBRT+H": 0.1021265737175275,
        "NN1": 0.10036191246836076,
        "NN2": 0.1028192520872786,
        "NN3": 0.0998841375006546,
        "NN4": 0.10167564722730568
      },
      "val_frac": 0.1,
      "mse": {
        "OLS-3": 0.011996579307909054,
        "ENet+H": 0.012251547316560713,
        "PCR": 0.012153783088779216,
        "PLS": 0.01208696323622382,
        "GLM+H": 0.012354050029586894,
        "GBRT+H": 0.011750310868913715,
        "NN1": 0.011956916320584154,
        "NN2": 0.011671150730987028,
        "NN3": 0.012014109739397975,
        "NN4": 0.011802422919179685
      },
      "n_obs_per_model": {
        "OLS-3": 24000,
        "ENet+H": 24000,
        "PCR": 24000,
        "PLS": 24000,
        "GLM+H": 24000,
        "GBRT+H": 24000,
        "NN1": 24000,
        "NN2": 24000,
        "NN3": 24000,
        "NN4": 24000
      },
      "eps": 1e-12,
      "method": "inverse_mse_normalized"
    },
    "_source": "recovered_from_ensemble_metadata.json",
    "_reconstruction": {
      "method": "inverse_mse_normalized_over_full_oos",
      "formula": "mse_m = mean((prediction_m - true_returns)^2); raw_w_m = 1/max(mse_m, eps); w_m = raw_w_m / sum(raw_w_m)",
      "eps": 1e-12,
      "source_files": [
        "outputs/future2026_mean_reversion/models/OLS-3.pkl",
        "outputs/future2026_mean_reversion/models/ENet+H.pkl",
        "outputs/future2026_mean_reversion/models/PCR.pkl",
        "outputs/future2026_mean_reversion/models/PLS.pkl",
        "outputs/future2026_mean_reversion/models/GLM+H.pkl",
        "outputs/future2026_mean_reversion/models/GBRT+H.pkl",
        "outputs/future2026_mean_reversion/models/NN1.pkl",
        "outputs/future2026_mean_reversion/models/NN2.pkl",
        "outputs/future2026_mean_reversion/models/NN3.pkl",
        "outputs/future2026_mean_reversion/models/NN4.pkl"
      ],
      "observations_per_model": {
        "OLS-3": 24000,
        "ENet+H": 24000,
        "PCR": 24000,
        "PLS": 24000,
        "GLM+H": 24000,
        "GBRT+H": 24000,
        "NN1": 24000,
        "NN2": 24000,
        "NN3": 24000,
        "NN4": 24000
      }
    }
  }
}